automail/__init__.py
automail/backup_mail.py
roelies_mailbot-0.0.1.dist-info/LICENSE
roelies_mailbot-0.0.1.dist-info/METADATA
roelies_mailbot-0.0.1.dist-info/WHEEL
roelies_mailbot-0.0.1.dist-info/top_level.txt
roelies_mailbot-0.0.1.dist-info/RECORD
